bober/__init__.py
bober/manager.py
bober/utils/__init__.py
bober-0.1.0a0.dist-info/LICENSE
bober-0.1.0a0.dist-info/METADATA
bober-0.1.0a0.dist-info/WHEEL
bober-0.1.0a0.dist-info/top_level.txt
bober-0.1.0a0.dist-info/RECORD
